Metadata-Version: 1.0
Name: chem-G5
Version: 1.0
Summary: Elementray reaction and reversible reaction
Home-page: https://github.com/CS207-G5/cs207-FinalProject
Author: Brianna, Thomas, Yujiao, Yi
Author-email: yi_zhai@g.harvard.edu
License: MIT
Platform: UNKNOWN
